ketaway/__init__.py
ketaway/mongkolchai.py
ketaway-0.0.4.dist-info/LICENSE.txt
ketaway-0.0.4.dist-info/METADATA
ketaway-0.0.4.dist-info/WHEEL
ketaway-0.0.4.dist-info/top_level.txt
ketaway-0.0.4.dist-info/RECORD
