Metadata-Version: 2.1
Name: ketaway
Version: 0.0.4
Summary: A small example package
Home-page: https://github.com/ketaway/ketaway
Author: Mongkolchai Worakhajee
Author-email: ketaway@gmail.com
License: UNKNOWN
Download-URL: https://github.com/ketaway/ketaway/archive/0.0.4.zip
Keywords: ketaway,Mongkolchai
Platform: UNKNOWN
Classifier: Development Status :: 3 - Alpha
Classifier: Intended Audience :: Developers
Classifier: Topic :: Software Development :: Build Tools
Classifier: License :: OSI Approved :: MIT License
Classifier: Programming Language :: Python :: 3
Classifier: Programming Language :: Python :: 3.4
Classifier: Programming Language :: Python :: 3.5
Classifier: Programming Language :: Python :: 3.6
Classifier: Programming Language :: Python :: 3.7
Requires-Python: >=3
